{
  "2nd.html": "2nd-5c248b07cfd6.html",
  "css/main.css": "css/main-abd2a3d30476.css",
  "img/8TH-1.png": "img/8TH-1-ce5c60b8ebc0.png",
  "img/TEE1.png": "img/TEE1-49c966d80bf4.png",
  "img/TEE10.png": "img/TEE10-7ed8110817ab.png",
  "img/TEE2.png": "img/TEE2-4b052d38612e.png",
  "img/TEE3.png": "img/TEE3-abaaeb5b1db1.png",
  "img/TEE4.png": "img/TEE4-2ab9add2d27d.png",
  "img/TEE5.png": "img/TEE5-a4887e15a6bd.png",
  "img/TEE6.png": "img/TEE6-a6931b35449b.png",
  "img/TEE7.png": "img/TEE7-27d40d288dec.png",
  "img/TEE8.png": "img/TEE8-eea5e89eb98e.png",
  "img/TEE9.png": "img/TEE9-229f4a193b35.png",
  "img/btn-buy.png": "img/btn-buy-d8545e2ec71d.png",
  "img/btn-buy2.png": "img/btn-buy2-00bef97f6b3b.png",
  "img/chrome.png": "img/chrome-c30b4c7c35b8.png",
  "img/dot.png": "img/dot-d1370cda5658.png",
  "img/down.png": "img/down-a79e317c9a53.png",
  "img/favicon.ico": "img/favicon.ico",
  "img/firefox.png": "img/firefox-bd58bacbb89e.png",
  "img/iconL.jpg": "img/iconL-c099d1e9444d.jpg",
  "img/iconM.jpg": "img/iconM-4461582cfebb.jpg",
  "img/myphoto.jpg": "img/myphoto-172a61623608.jpg",
  "img/up.png": "img/up-70f25fdacd84.png",
  "index.html": "index.html",
  "js/main.js": "js/main-f4a33002550d.js"
}